setup.cfg
setup.py
trueface/__init__.py
trueface/api.py
trueface/detector.py
trueface/enroll.py
trueface/helper.py
trueface/logo.png
trueface/mtcnn_detector.py
trueface/server.py
trueface/trueface.py
trueface/utilities.py
trueface/video.py
trueface.egg-info/PKG-INFO
trueface.egg-info/SOURCES.txt
trueface.egg-info/dependency_links.txt
trueface.egg-info/entry_points.txt
trueface.egg-info/not-zip-safe
trueface.egg-info/requires.txt
trueface.egg-info/top_level.txt
trueface/model/__init__.py
trueface/model/det1-0001.params
trueface/model/det1-symbol.json
trueface/model/det1.caffemodel
trueface/model/det1.prototxt
trueface/model/det2-0001.params
trueface/model/det2-symbol.json
trueface/model/det2.caffemodel
trueface/model/det2.prototxt
trueface/model/det3-0001.params
trueface/model/det3-symbol.json
trueface/model/det3.caffemodel
trueface/model/det3.prototxt
trueface/model/det4-0001.params
trueface/model/det4-symbol.json
trueface/model/det4.caffemodel
trueface/model/det4.prototxt