Metadata-Version: 1.0
Name: trueface
Version: 0.32
Summary: Trueface.ai Face Recognition
Home-page: https://github.com/getchui/truefacesdk
Author: Nezare Chafni
Author-email: nchafni@truface.ai
License: MIT
Platform: UNKNOWN
